ndlpy/__init__.py
ndlpy/access/download.py
ndlpy/access/io.py
ndlpy/assess/data.py
ndlpy/config/#interface-cg.py#
ndlpy/config/context.py
ndlpy/config/defaults.yml
ndlpy/config/interface-cg.py
ndlpy/config/interface.py
ndlpy/config/interface.py~
ndlpy/config/old_interface.py
ndlpy/convert.py
ndlpy/exceptions.py
ndlpy/log.py
ndlpy/ndlappointment.py
ndlpy/ndlcal.py
ndlpy/ndlcgi.py
ndlpy/ndlconvert.py
ndlpy/ndlexpenses.py
ndlpy/ndlimage.py
ndlpy/ndlmarkdown.py
ndlpy/ndlstrutil.py
ndlpy/ndltext.py
ndlpy/old_data.py
ndlpy/test.xlsx
ndlpy/tests/#test_access_io.py#
ndlpy/tests/ndlpy.log
ndlpy/tests/talk_tests.py
ndlpy/tests/test_access_download.py
ndlpy/tests/test_access_io.py
ndlpy/tests/test_assess_data.py
ndlpy/tests/test_config_context.py
ndlpy/tests/test_config_interface.py
ndlpy/tests/test_util_dataframe.py
ndlpy/tests/test_util_files.py
ndlpy/tests/test_util_liquid.py
ndlpy/tests/test_util_misc.py
ndlpy/tests/test_util_talk.py
ndlpy/tests/test_util_tex.py
ndlpy/tests/test_util_yaml.py
ndlpy/util/dataframe.py
ndlpy/util/fake.py
ndlpy/util/files.py
ndlpy/util/html.py
ndlpy/util/liquid.py
ndlpy/util/misc.py
ndlpy/util/talk.py
ndlpy/util/tex.py
ndlpy/util/yaml.py
ndlpy-0.2.1.dist-info/METADATA
ndlpy-0.2.1.dist-info/WHEEL
ndlpy-0.2.1.dist-info/entry_points.txt
ndlpy-0.2.1.dist-info/RECORD
